pyrolinks/__init__.py
pyrolinks/client.py
pyrolinks/core.py
pyrolinks/errors.py
pyrolinks/server.py
pyrolinks/utils.py
pyrolinks-3.1.dist-info/licenses/LICENSE
pyrolinks-3.1.dist-info/METADATA
pyrolinks-3.1.dist-info/WHEEL
pyrolinks-3.1.dist-info/top_level.txt
pyrolinks-3.1.dist-info/RECORD
