Metadata-Version: 2.4
Name: pyrolinks
Version: 3.1
Summary: Generate direct download links for Telegram media using Pyrogram
Home-page: https://github.com/MrHamid97/PyroLink
Author: MrHamid97
Author-email: hamiddrgz@gmail.com
License: MIT
Classifier: Programming Language :: Python :: 3
Classifier: License :: OSI Approved :: MIT License
Classifier: Operating System :: OS Independent
Requires-Python: >=3.8
License-File: LICENSE
Requires-Dist: kurigram>=2.2
Requires-Dist: aiohttp>=3.8
Dynamic: license-file
